colorchecker2cielab/__init__.py
colorchecker2cielab/_modidx.py
colorchecker2cielab/basiccolor.py
colorchecker2cielab/cielab.py
colorchecker2cielab/core.py
colorchecker2cielab/extractor.py
colorchecker2cielab/metamorfoze.py
colorchecker2cielab/utils.py
colorchecker2cielab-0.0.3.dist-info/LICENSE
colorchecker2cielab-0.0.3.dist-info/METADATA
colorchecker2cielab-0.0.3.dist-info/WHEEL
colorchecker2cielab-0.0.3.dist-info/entry_points.txt
colorchecker2cielab-0.0.3.dist-info/top_level.txt
colorchecker2cielab-0.0.3.dist-info/RECORD
