Metadata-Version: 2.1
Name: colorchecker2cielab
Version: 0.0.3
Summary: Extract CIELAB values from color managed TIF images
Home-page: https://github.com/fligt/colorchecker2cielab
Author: Frank Ligterink
Author-email: frank.ligterink@gmail.com
License: MIT License
Keywords: color-science tif colorchecker cielab
Classifier: Development Status :: 4 - Beta
Classifier: Intended Audience :: Developers
Classifier: Natural Language :: English
Classifier: Programming Language :: Python :: 3.7
Classifier: Programming Language :: Python :: 3.8
Classifier: Programming Language :: Python :: 3.9
Classifier: Programming Language :: Python :: 3.10
Classifier: License :: OSI Approved :: MIT License
Requires-Python: >=3.7
License-File: LICENSE
Requires-Dist: scikit-image
Requires-Dist: matplotlib
Requires-Dist: colour-science
Requires-Dist: scipy
Requires-Dist: pandas
Requires-Dist: requests
Requires-Dist: tqdm
Requires-Dist: openpyxl
Provides-Extra: dev
